MANIFEST.in
NEWS.md
README.rst
setup.py
bin/hod
etc/hod/HBase-1.0.2/datanode.conf
etc/hod/HBase-1.0.2/hbase-master.conf
etc/hod/HBase-1.0.2/hod.conf
etc/hod/HBase-1.0.2/namenode.conf
etc/hod/HBase-1.0.2/regionserver.conf
etc/hod/HBase-1.0.2/screen.conf
etc/hod/HBase-1.0.2/zookeeper.conf
etc/hod/Hadoop-2.3.0-cdh5.0.0/hod.conf
etc/hod/Hadoop-2.3.0-cdh5.0.0/nodemanager.conf
etc/hod/Hadoop-2.3.0-cdh5.0.0/resourcemanager.conf
etc/hod/Hadoop-2.3.0-cdh5.0.0/screen.conf
etc/hod/Hadoop-2.5.0-cdh5.3.1-gpfs/hod.conf
etc/hod/Hadoop-2.5.0-cdh5.3.1-gpfs/nodemanager.conf
etc/hod/Hadoop-2.5.0-cdh5.3.1-gpfs/resourcemanager.conf
etc/hod/Hadoop-2.5.0-cdh5.3.1-gpfs/screen.conf
etc/hod/Hadoop-2.5.0-cdh5.3.1-native/hod.conf
etc/hod/Hadoop-2.5.0-cdh5.3.1-native/nodemanager.conf
etc/hod/Hadoop-2.5.0-cdh5.3.1-native/resourcemanager.conf
etc/hod/Hadoop-2.5.0-cdh5.3.1-native/screen.conf
etc/hod/Hadoop-2.6.0-cdh5.4.5-native/hod.conf
etc/hod/Hadoop-2.6.0-cdh5.4.5-native/nodemanager.conf
etc/hod/Hadoop-2.6.0-cdh5.4.5-native/resourcemanager.conf
etc/hod/Hadoop-2.6.0-cdh5.4.5-native/screen.conf
etc/hod/Hadoop-on-lustre2/hod.conf
etc/hod/Hadoop-on-lustre2/nodemanager.conf
etc/hod/Hadoop-on-lustre2/resourcemanager.conf
etc/hod/Hadoop-on-lustre2/screen.conf
etc/hod/IPython-notebook-3.2.1/hod.conf
etc/hod/IPython-notebook-3.2.1/ipython.conf
etc/hod/IPython-notebook-3.2.1/nodemanager.conf
etc/hod/IPython-notebook-3.2.1/resourcemanager.conf
etc/hod/IPython-notebook-3.2.1/screen.conf
etc/hod/IPython-notebook-3.2.1/start-notebook.sh
etc/hod/IPython-notebook-3.2.3/hod.conf
etc/hod/IPython-notebook-3.2.3/ipython.conf
etc/hod/IPython-notebook-3.2.3/nodemanager.conf
etc/hod/IPython-notebook-3.2.3/resourcemanager.conf
etc/hod/IPython-notebook-3.2.3/screen.conf
etc/hod/IPython-notebook-3.2.3/start-notebook.sh
etc/hod/IPython-notebook-4.2.0/hod.conf
etc/hod/IPython-notebook-4.2.0/ipython.conf
etc/hod/IPython-notebook-4.2.0/nodemanager.conf
etc/hod/IPython-notebook-4.2.0/resourcemanager.conf
hanythingondemand.egg-info/PKG-INFO
hanythingondemand.egg-info/SOURCES.txt
hanythingondemand.egg-info/dependency_links.txt
hanythingondemand.egg-info/requires.txt
hanythingondemand.egg-info/top_level.txt
hanythingondemand.egg-info/zip-safe
