Metadata-Version: 1.2
Name: hanythingondemand
Version: 3.2.3
Summary: UNKNOWN
Home-page: UNKNOWN
Author: ['stijn.deweirdt@ugent.be', 'jens.timmerman@ugent.be', 'ewan.higgs@ugent.be']
Maintainer: ['stijn.deweirdt@ugent.be', 'jens.timmerman@ugent.be', 'ewan.higgs@ugent.be']
License: GPL v2
Platform: UNKNOWN
Classifier: Programming Language :: Python :: 2
